{
  "version": "5",
  "dialect": "pg",
  "entries": [
    {
      "idx": 0,
      "version": "5",
      "when": 1715717251533,
      "tag": "0000_free_thaddeus_ross",
      "breakpoints": true
    },
    {
      "idx": 1,
      "version": "5",
      "when": 1715718181980,
      "tag": "0001_lowly_corsair",
      "breakpoints": true
    },
    {
      "idx": 2,
      "version": "5",
      "when": 1715975268117,
      "tag": "0002_military_master_mold",
      "breakpoints": true
    },
    {
      "idx": 3,
      "version": "5",
      "when": 1716018704375,
      "tag": "0003_dark_warhawk",
      "breakpoints": true
    }
  ]
}